netvision/ChartGenerator.py
netvision/ConfusionMatrixGenerator.py
netvision/HtmlGenerator.py
netvision/MeshGenerator.py
netvision/Table.py
netvision/__init__.py
netvision/colormap.npy
netvision/utils.py
netvision/js/Chart.bundle.min.js
netvision/js/Detector.js
netvision/js/MTLLoader.js
netvision/js/OBJLoader.js
netvision/js/OrbitControls.js
netvision/js/three.js
netvision-1.1.2.dist-info/LICENSE
netvision-1.1.2.dist-info/METADATA
netvision-1.1.2.dist-info/WHEEL
netvision-1.1.2.dist-info/top_level.txt
netvision-1.1.2.dist-info/RECORD
