Metadata-Version: 2.1
Name: netvision
Version: 1.1.2
Summary: Fuel your collaborations by sending awesome webpage results. Forget about HTML and CSS and Javascript, just effortlessly use Python.
Home-page: https://github.com/palanglois/netvision
Author: Pierre-Alain Langlois, Thibault Groueix
Author-email: 
License: MIT
License-File: LICENSE
Requires-Dist: numpy
